[
	{
		"identifier": "id",
		"type": "number",
		"name": "Id",
		"width": "80px",
		"minWidth": "80px",
		"alignment": "left",
		"hint": "Номер",
		"visible": true,
		"position": 1,
		"filter": false,
		"inlist": true
	},
	{
		"identifier": "shortName",
		"type": "string",
		"name": "ShortName",
		"width": "150px",
		"minWidth": "150px",
		"alignment": "left",
		"hint": "Наименование",
		"visible": true,
		"position": 2,
		"filter": false,
		"inlist": true
	},
	{
		"identifier": "displayName",
		"type": "string",
		"name": "DisplayName",
		"width": "150px",
		"minWidth": "150px",
		"alignment": "left",
		"hint": "Полное наименование",
		"visible": true,
		"position": 3,
		"filter": false,
		"inlist": true
	},
	{
		"identifier": "bin",
		"type": "string",
		"name": "BIN",
		"width": "150px",
		"minWidth": "150px",
		"alignment": "left",
		"hint": "БИН",
		"visible": true,
		"position": 4,
		"filter": false,
		"inlist": true
	}
]
