[
	{
		"identifier": "id",
		"name": "ID",
		"hint": "Внутренний номер",
		"type": "number",
		"position": 1,
		"visible": true,
		"width": "80px",
		"minWidth": "80px",
		"alignment": "left"
	},
	{
		"identifier": "uuid",
		"name": "UUID",
		"hint": "UUID",
		"type": "string",
		"position": 2,
		"visible": false,
		"inlist": false,
		"width": "0px",
		"minWidth": "0px",
		"alignment": "left"
	},
	{
		"identifier": "shortName",
		"name": "Наименование",
		"hint": "Наименование номенклатуры",
		"type": "string",
		"position": 3,
		"visible": true,
		"width": "250px",
		"minWidth": "80px",
		"alignment": "left"
	},
	{
		"identifier": "sku",
		"name": "Артикул",
		"hint": "Артикул",
		"type": "string",
		"position": 4,
		"visible": true,
		"width": "130px",
		"minWidth": "80px",
		"alignment": "left"
	},
	{
		"identifier": "brand.shortName",
		"name": "Бренд",
		"hint": "Бренд",
		"type": "string",
		"position": 5,
		"visible": true,
		"width": "150px",
		"minWidth": "80px",
		"alignment": "left"
	},
	{
		"identifier": "unitOfMeasure.shortName",
		"name": "Ед. изм.",
		"hint": "Единица измерения",
		"type": "string",
		"position": 6,
		"visible": true,
		"width": "100px",
		"minWidth": "70px",
		"alignment": "left"
	}
]
